{
  "id": "687df774000000000b02cc48",
  "type": "video",
  "title": "直播精彩片段，如何评估大模型效用",
  "desc": "2024年是「Agent元年」的共识正在形成，从 AutoGPT 到 Devin，从 MCP 到 A2A、ANP，智能体浪潮正在悄然改写我们的工作与生活方式。我们离“每人一个智能助理”的时代还有多远？\n最新一期的 GAIR Live 线上圆桌论坛将围绕「Agent」话题展开，5位在智能体一线的投资人、创业者与技术布道者，将共同探讨这个正在升温的关键议题。\n大模型如何有效评估，来听听专家们怎么说\n\t\n#大模型 #人工智能 #aiagent #evaluation #科技",
  "tags": [],
  "author": "AI科技评论",
  "authorId": "62cbf6d20000000002003fde",
  "time": 1753085812000,
  "ipLocation": "",
  "likes": "9",
  "images": [
    "http://sns-web-i10.rednotecdn.com/202606091327/ddada714b6018d0731b84ba73b70c24d/spectrum/1040g34o31k6mkgh32a0g5ombur90gfuutvl99lg!nd_dft_wlteh_webp_3?src=A"
  ],
  "video": "http://sns-v11.rednotecdn.com/stream/1/110/259/01e87df65a811f2c01037003982c0f773f_259.mp4",
  "source_url": "https://www.rednote.com/user/profile/6181a3eb000000001000da07/687df774000000000b02cc48?xsec_token=AB3FIdUBrc_cDdiCwQzQ1hFWiTfJ7EHeqGso-Dn_EoF_o=&xsec_source=pc_collect"
}