{
  "id": "69638fc4000000002103199e",
  "type": "video",
  "title": "姚顺雨讲述的论文《React》&《Reflection》",
  "desc": "#Agent[话题]# #大模型[话题]# #AI学习[话题]# #采访[话题]# #算法[话题]# #强化学习[话题]# #姚顺雨[话题]# #Reflection[话题]# #React[话题]# #人工智能未来[话题]#",
  "tags": [
    "Agent",
    "大模型",
    "AI学习",
    "采访",
    "算法",
    "强化学习",
    "姚顺雨",
    "Reflection",
    "React",
    "人工智能未来"
  ],
  "author": "在地球上服役的小麻瓜",
  "authorId": "67e288b4000000000a03c42e",
  "time": 1768132548000,
  "ipLocation": "",
  "likes": "3,662",
  "images": [
    "http://sns-web-i10.rednotecdn.com/202606090950/4cfbb2b25470b21273850019aae404ce/spectrum/1040g34o31r6tem0pmu105pv2h2q2nh1em2mien8!nd_dft_wgth_webp_3?src=A"
  ],
  "video": "http://sns-v8.rednotecdn.com/stream/79/110/259/01e9638f949da75f010370039baceb85ed_259.mp4",
  "source_url": "https://www.rednote.com/user/profile/6181a3eb000000001000da07/69638fc4000000002103199e?xsec_token=AB9szmyOuQRm6c2sU_xY_FkiNeb03MWcT_HFaJlH8R58E=&xsec_source=pc_collect"
}